hardsploit_gui/__init__.py
hardsploit_gui/classes/CAN/can_baudrate.py
hardsploit_gui/classes/CAN/can_settings.py
hardsploit_gui/classes/I2C/i2c_command.py
hardsploit_gui/classes/I2C/i2c_commands.py
hardsploit_gui/classes/I2C/i2c_read.py
hardsploit_gui/classes/I2C/i2c_settings.py
hardsploit_gui/classes/I2C/i2c_write.py
hardsploit_gui/classes/NRF24L01/nrf_commands.py
hardsploit_gui/classes/NRF24L01/nrf_scan.py
hardsploit_gui/classes/NRF24L01/nrf_settings.py
hardsploit_gui/classes/NRF24L01/nrf_sniffer.py
hardsploit_gui/classes/SPI/spi_commands.py
hardsploit_gui/classes/SPI/spi_read.py
hardsploit_gui/classes/SPI/spi_settings.py
hardsploit_gui/classes/SPI/spi_sniffer.py
hardsploit_gui/classes/SPI/spi_write.py
hardsploit_gui/classes/__init__.py
hardsploit_gui/classes/chip_clone.py
hardsploit_gui/classes/chip_editor.py
hardsploit_gui/classes/chip_management.py
hardsploit_gui/classes/command_editor.py
hardsploit_gui/classes/command_table.py
hardsploit_gui/classes/console.py
hardsploit_gui/classes/error_msg.py
hardsploit_gui/classes/export.py
hardsploit_gui/classes/export_manager.py
hardsploit_gui/classes/firmware.py
hardsploit_gui/classes/generic_commands.py
hardsploit_gui/classes/import_datas.py
hardsploit_gui/classes/progress_bar.py
hardsploit_gui/classes/signal_mapper.py
hardsploit_gui/classes/swd/swd.py
hardsploit_gui/classes/swd/swd_settings.py
hardsploit_gui/classes/tab_management.py
hardsploit_gui/classes/uart/uart_baudrate.py
hardsploit_gui/classes/uart/uart_console.py
hardsploit_gui/classes/uart/uart_settings.py
hardsploit_gui/classes/utils.py
hardsploit_gui/classes/wire_helper.py
hardsploit_gui/db/__init__.py
hardsploit_gui/db/hardsploit.db
hardsploit_gui/db/models.py
hardsploit_gui/gui/__init__.py
hardsploit_gui/gui/gui_can_baudrate.py
hardsploit_gui/gui/gui_can_read.py
hardsploit_gui/gui/gui_can_settings.py
hardsploit_gui/gui/gui_can_sniffer.py
hardsploit_gui/gui/gui_can_write.py
hardsploit_gui/gui/gui_chip_clone.py
hardsploit_gui/gui/gui_chip_editor.py
hardsploit_gui-2.0.0.dist-info/LICENSE
hardsploit_gui-2.0.0.dist-info/METADATA
hardsploit_gui-2.0.0.dist-info/WHEEL
hardsploit_gui-2.0.0.dist-info/entry_points.txt
hardsploit_gui-2.0.0.dist-info/RECORD
