Metadata-Version: 2.1
Name: hardsploit-gui
Version: 2.0.0
Summary: QT graphical interface for Hardsploit HW access
Home-page: https://github.com/serma-safety-security/hardsploit_gui
License: LGPL-3.0-only
Author: PERIES Mickaël
Author-email: m.peries@serma.com
Requires-Python: >=3.9,<3.13
Classifier: License :: OSI Approved :: GNU Lesser General Public License v3 (LGPLv3)
Classifier: Operating System :: OS Independent
Classifier: Programming Language :: Python :: 3
Classifier: Programming Language :: Python :: 3.9
Classifier: Programming Language :: Python :: 3.10
Classifier: Programming Language :: Python :: 3.11
Classifier: Programming Language :: Python :: 3.12
Requires-Dist: PySide6 (>=6.7,<7.0)
Requires-Dist: hardsploit
Requires-Dist: peewee (>=3.17,<4.0)
Project-URL: Bug Tracker, https://github.com/serma-safety-security/hardsploit/issues
Project-URL: Documentation, https://github.com/serma-safety-security/hardsploit_gui/wiki
